[{"childItems": [{"childItems": [{"childItems": [{"childItems": [], "text": "czarny theme", "type": "note", "date": "", "color": "NO_COLOR", "estimate": "", "expanded": true, "quicklink_expanded": false, "search_text": "", "shortcut": null, "saved_root_item_creation_date_time": null, "creation_date_time": 1581941694.7133312, "selected": false, "planned": 0, "planned_order": 0}, {"childItems": [], "text": "opisy w polach tekstowych", "type": "note", "date": "", "color": "NO_COLOR", "estimate": "", "expanded": true, "quicklink_expanded": false, "search_text": "", "shortcut": null, "saved_root_item_creation_date_time": null, "creation_date_time": 1582286516.9410048, "selected": false, "planned": 0, "planned_order": 0}, {"childItems": [], "text": "kolory przycisk\u00f3w?", "type": "note", "date": "", "color": "NO_COLOR", "estimate": "", "expanded": true, "quicklink_expanded": false, "search_text": "", "shortcut": null, "saved_root_item_creation_date_time": null, "creation_date_time": 1582286507.877458, "selected": false, "planned": 0, "planned_order": 0}, {"childItems": [], "text": "zrobi\u0107 black theme", "type": "note", "date": "", "color": "NO_COLOR", "estimate": "", "expanded": true, "quicklink_expanded": false, "search_text": "", "shortcut": null, "saved_root_item_creation_date_time": null, "creation_date_time": 1581686148.9300096, "selected": false, "planned": 0, "planned_order": 0}], "text": "settings doda\u0107", "type": "note", "date": "", "color": "NO_COLOR", "estimate": "", "expanded": true, "quicklink_expanded": false, "search_text": "", "shortcut": null, "saved_root_item_creation_date_time": null, "creation_date_time": 1582286501.7499597, "selected": false, "planned": 0, "planned_order": 0}, {"childItems": [{"childItems": [], "text": "z czarnym t\u0142em itp.", "type": "note", "date": "", "color": "NO_COLOR", "estimate": "", "expanded": true, "quicklink_expanded": false, "search_text": "", "shortcut": null, "saved_root_item_creation_date_time": null, "creation_date_time": 1582626821.4963248, "selected": false, "planned": 0, "planned_order": 0}], "text": "dodac obrazki z aplikacji", "type": "note", "date": "", "color": "NO_COLOR", "estimate": "", "expanded": true, "quicklink_expanded": false, "search_text": "", "shortcut": null, "saved_root_item_creation_date_time": null, "creation_date_time": 1582622417.5192394, "selected": false, "planned": 0, "planned_order": 0}, {"childItems": [{"childItems": [], "text": "czarny them oraz kolorowanie influences", "type": "note", "date": "", "color": "NO_COLOR", "estimate": "", "expanded": true, "quicklink_expanded": false, "search_text": "", "shortcut": null, "saved_root_item_creation_date_time": null, "creation_date_time": 1582626835.9440079, "selected": false, "planned": 0, "planned_order": 0}], "text": "dopracowa\u0107 vizualnie to", "type": "note", "date": "", "color": "NO_COLOR", "estimate": "", "expanded": true, "quicklink_expanded": false, "search_text": "", "shortcut": null, "saved_root_item_creation_date_time": null, "creation_date_time": 1581939789.461449, "selected": false, "planned": 0, "planned_order": 0}, {"childItems": [{"childItems": [], "text": "doda\u0107 przycisk po  kt\u00f3rym b\u0119d\u0105 widoczne odpowiednie tabele", "type": "note", "date": "", "color": "NO_COLOR", "estimate": "", "expanded": true, "quicklink_expanded": false, "search_text": "", "shortcut": null, "saved_root_item_creation_date_time": null, "creation_date_time": 1582284372.4629655, "selected": false, "planned": 0, "planned_order": 0}], "text": "doda\u0107 opcjonalne dodawanie i ukrywanie p\u00f3l", "type": "note", "date": "", "color": "NO_COLOR", "estimate": "", "expanded": true, "quicklink_expanded": false, "search_text": "", "shortcut": null, "saved_root_item_creation_date_time": null, "creation_date_time": 1582284358.983573, "selected": false, "planned": 0, "planned_order": 0}, {"childItems": [], "text": "doda\u0107 obrazki", "type": "note", "date": "", "color": "NO_COLOR", "estimate": "", "expanded": true, "quicklink_expanded": false, "search_text": "", "shortcut": null, "saved_root_item_creation_date_time": null, "creation_date_time": 1582622372.9457452, "selected": false, "planned": 0, "planned_order": 0}, {"childItems": [], "text": "na t\u0105 chwil\u0119 negatywnych warto\u015bci nie wida\u0107, wi\u0119c troche problematyczne to jest", "type": "note", "date": "", "color": "NO_COLOR", "estimate": "", "expanded": true, "quicklink_expanded": false, "search_text": "", "shortcut": null, "saved_root_item_creation_date_time": null, "creation_date_time": 1581934862.3185768, "selected": false, "planned": 0, "planned_order": 0}, {"childItems": [], "text": "Podliczanie obecnie ustawionych warto\u015bci", "type": "note", "date": "", "color": "NO_COLOR", "estimate": "", "expanded": true, "quicklink_expanded": false, "search_text": "", "shortcut": null, "saved_root_item_creation_date_time": null, "creation_date_time": 1581595908.2604337, "selected": false, "planned": 0, "planned_order": 0}, {"childItems": [{"childItems": [], "text": "ze wszysytkich plus i minus warto\u015bci", "type": "note", "date": "", "color": "NO_COLOR", "estimate": "", "expanded": true, "quicklink_expanded": false, "search_text": "", "shortcut": null, "saved_root_item_creation_date_time": null, "creation_date_time": 1581596001.5944712, "selected": false, "planned": 0, "planned_order": 0}], "text": "pole kt\u00f3ra oblicza sumaryczn\u0105 warto\u015b\u0107", "type": "note", "date": "", "color": "NO_COLOR", "estimate": "", "expanded": true, "quicklink_expanded": false, "search_text": "", "shortcut": null, "saved_root_item_creation_date_time": null, "creation_date_time": 1581595975.6828687, "selected": false, "planned": 0, "planned_order": 0}, {"childItems": [], "text": "Niech zapami\u0119tuje wprowadzony tekst.", "type": "note", "date": "", "color": "NO_COLOR", "estimate": "", "expanded": true, "quicklink_expanded": false, "search_text": "", "shortcut": null, "saved_root_item_creation_date_time": null, "creation_date_time": 1581338488.60448, "selected": false, "planned": 0, "planned_order": 0}, {"childItems": [], "text": "niech zapisuje warto\u015b\u0107 wype\u0142nionych linii", "type": "note", "date": "", "color": "NO_COLOR", "estimate": "", "expanded": true, "quicklink_expanded": false, "search_text": "", "shortcut": null, "saved_root_item_creation_date_time": null, "creation_date_time": 1581338986.9989858, "selected": false, "planned": 0, "planned_order": 0}, {"childItems": [], "text": "pokolorowa\u0107 warto\u015bci przesuwanych element\u00f3w", "type": "note", "date": "", "color": "NO_COLOR", "estimate": "", "expanded": true, "quicklink_expanded": false, "search_text": "", "shortcut": null, "saved_root_item_creation_date_time": null, "creation_date_time": 1581668941.524545, "selected": false, "planned": 0, "planned_order": 0}, {"childItems": [], "text": "powyr\u00f3wnywa\u0107 kreski w aplikacji, zeby by\u0142a lepsza symetria, bo wygl\u0105da semi pro", "type": "note", "date": "", "color": "NO_COLOR", "estimate": "", "expanded": true, "quicklink_expanded": false, "search_text": "", "shortcut": null, "saved_root_item_creation_date_time": null, "creation_date_time": 1581426341.8646152, "selected": false, "planned": 0, "planned_order": 0}, {"childItems": [], "text": "doda\u0107 czarny theme", "type": "note", "date": "", "color": "NO_COLOR", "estimate": "", "expanded": true, "quicklink_expanded": false, "search_text": "", "shortcut": null, "saved_root_item_creation_date_time": null, "creation_date_time": 1581668952.7247138, "selected": false, "planned": 0, "planned_order": 0}, {"childItems": [], "text": "poprawi\u0107 landplace design, np. przez wymuszenie tego kt\u00f3ry jest", "type": "note", "date": "", "color": "NO_COLOR", "estimate": "", "expanded": true, "quicklink_expanded": false, "search_text": "", "shortcut": null, "saved_root_item_creation_date_time": null, "creation_date_time": 1581667439.334428, "selected": false, "planned": 0, "planned_order": 0}, {"childItems": [], "text": "stworzy\u0107 obrazki do aplikacji", "type": "note", "date": "", "color": "NO_COLOR", "estimate": "", "expanded": true, "quicklink_expanded": false, "search_text": "", "shortcut": null, "saved_root_item_creation_date_time": null, "creation_date_time": 1581668994.5962288, "selected": false, "planned": 0, "planned_order": 0}, {"childItems": [], "text": "warto\u015bci negatywne s\u0105 obrucone o 180 stopni", "type": "note", "date": "", "color": "NO_COLOR", "estimate": "", "expanded": true, "quicklink_expanded": false, "search_text": "", "shortcut": null, "saved_root_item_creation_date_time": null, "creation_date_time": 1581681885.8263483, "selected": false, "planned": 0, "planned_order": 0}, {"childItems": [], "text": "usun\u0105\u0107 obw\u00f3dk\u0119 z przesuwanych negative warto\u015bci", "type": "note", "date": "", "color": "NO_COLOR", "estimate": "", "expanded": true, "quicklink_expanded": false, "search_text": "", "shortcut": null, "saved_root_item_creation_date_time": null, "creation_date_time": 1581681872.0023775, "selected": false, "planned": 0, "planned_order": 0}, {"childItems": [], "text": "doda\u0107 apke do AppStore'a", "type": "note", "date": "", "color": "NO_COLOR", "estimate": "", "expanded": true, "quicklink_expanded": false, "search_text": "", "shortcut": null, "saved_root_item_creation_date_time": null, "creation_date_time": 1581668986.436446, "selected": false, "planned": 0, "planned_order": 0}], "text": "Sko\u0144czy\u0107 bucket app", "type": "note", "date": "", "color": "NO_COLOR", "estimate": "", "expanded": true, "quicklink_expanded": false, "search_text": "", "shortcut": null, "saved_root_item_creation_date_time": null, "creation_date_time": 1581338059.9101033, "selected": false, "planned": 0, "planned_order": 0}, {"childItems": [{"childItems": [{"childItems": [], "text": "czarny theme", "type": "note", "date": "", "color": "NO_COLOR", "estimate": "", "expanded": true, "quicklink_expanded": false, "search_text": "", "shortcut": null, "saved_root_item_creation_date_time": null, "creation_date_time": 1581941694.7133312, "selected": false, "planned": 0, "planned_order": 0}, {"childItems": [], "text": "opisy w polach tekstowych", "type": "note", "date": "", "color": "NO_COLOR", "estimate": "", "expanded": true, "quicklink_expanded": false, "search_text": "", "shortcut": null, "saved_root_item_creation_date_time": null, "creation_date_time": 1582286516.9410048, "selected": false, "planned": 0, "planned_order": 0}, {"childItems": [], "text": "kolory przycisk\u00f3w?", "type": "note", "date": "", "color": "NO_COLOR", "estimate": "", "expanded": true, "quicklink_expanded": false, "search_text": "", "shortcut": null, "saved_root_item_creation_date_time": null, "creation_date_time": 1582286507.877458, "selected": false, "planned": 0, "planned_order": 0}, {"childItems": [], "text": "zrobi\u0107 black theme", "type": "note", "date": "", "color": "NO_COLOR", "estimate": "", "expanded": true, "quicklink_expanded": false, "search_text": "", "shortcut": null, "saved_root_item_creation_date_time": null, "creation_date_time": 1581686148.9300096, "selected": false, "planned": 0, "planned_order": 0}], "text": "settings doda\u0107", "type": "note", "date": "", "color": "NO_COLOR", "estimate": "", "expanded": true, "quicklink_expanded": false, "search_text": "", "shortcut": null, "saved_root_item_creation_date_time": null, "creation_date_time": 1582286501.7499597, "selected": false, "planned": 0, "planned_order": 0}, {"childItems": [{"childItems": [], "text": "z czarnym t\u0142em itp.", "type": "note", "date": "", "color": "NO_COLOR", "estimate": "", "expanded": true, "quicklink_expanded": false, "search_text": "", "shortcut": null, "saved_root_item_creation_date_time": null, "creation_date_time": 1582626821.4963248, "selected": false, "planned": 0, "planned_order": 0}], "text": "dodac obrazki z aplikacji", "type": "note", "date": "", "color": "NO_COLOR", "estimate": "", "expanded": true, "quicklink_expanded": false, "search_text": "", "shortcut": null, "saved_root_item_creation_date_time": null, "creation_date_time": 1582622417.5192394, "selected": false, "planned": 0, "planned_order": 0}, {"childItems": [{"childItems": [], "text": "czarny them oraz kolorowanie influences", "type": "note", "date": "", "color": "NO_COLOR", "estimate": "", "expanded": true, "quicklink_expanded": false, "search_text": "", "shortcut": null, "saved_root_item_creation_date_time": null, "creation_date_time": 1582626835.9440079, "selected": false, "planned": 0, "planned_order": 0}], "text": "dopracowa\u0107 vizualnie to", "type": "note", "date": "", "color": "NO_COLOR", "estimate": "", "expanded": true, "quicklink_expanded": false, "search_text": "", "shortcut": null, "saved_root_item_creation_date_time": null, "creation_date_time": 1581939789.461449, "selected": false, "planned": 0, "planned_order": 0}, {"childItems": [{"childItems": [], "text": "doda\u0107 przycisk po  kt\u00f3rym b\u0119d\u0105 widoczne odpowiednie tabele", "type": "note", "date": "", "color": "NO_COLOR", "estimate": "", "expanded": true, "quicklink_expanded": false, "search_text": "", "shortcut": null, "saved_root_item_creation_date_time": null, "creation_date_time": 1582284372.4629655, "selected": false, "planned": 0, "planned_order": 0}], "text": "doda\u0107 opcjonalne dodawanie i ukrywanie p\u00f3l", "type": "note", "date": "", "color": "NO_COLOR", "estimate": "", "expanded": true, "quicklink_expanded": false, "search_text": "", "shortcut": null, "saved_root_item_creation_date_time": null, "creation_date_time": 1582284358.983573, "selected": false, "planned": 0, "planned_order": 0}, {"childItems": [], "text": "doda\u0107 obrazki", "type": "note", "date": "", "color": "NO_COLOR", "estimate": "", "expanded": true, "quicklink_expanded": false, "search_text": "", "shortcut": null, "saved_root_item_creation_date_time": null, "creation_date_time": 1582622372.9457452, "selected": false, "planned": 0, "planned_order": 0}, {"childItems": [], "text": "na t\u0105 chwil\u0119 negatywnych warto\u015bci nie wida\u0107, wi\u0119c troche problematyczne to jest", "type": "note", "date": "", "color": "NO_COLOR", "estimate": "", "expanded": true, "quicklink_expanded": false, "search_text": "", "shortcut": null, "saved_root_item_creation_date_time": null, "creation_date_time": 1581934862.3185768, "selected": false, "planned": 0, "planned_order": 0}, {"childItems": [], "text": "Podliczanie obecnie ustawionych warto\u015bci", "type": "note", "date": "", "color": "NO_COLOR", "estimate": "", "expanded": true, "quicklink_expanded": false, "search_text": "", "shortcut": null, "saved_root_item_creation_date_time": null, "creation_date_time": 1581595908.2604337, "selected": false, "planned": 0, "planned_order": 0}, {"childItems": [{"childItems": [], "text": "ze wszysytkich plus i minus warto\u015bci", "type": "note", "date": "", "color": "NO_COLOR", "estimate": "", "expanded": true, "quicklink_expanded": false, "search_text": "", "shortcut": null, "saved_root_item_creation_date_time": null, "creation_date_time": 1581596001.5944712, "selected": false, "planned": 0, "planned_order": 0}], "text": "pole kt\u00f3ra oblicza sumaryczn\u0105 warto\u015b\u0107", "type": "note", "date": "", "color": "NO_COLOR", "estimate": "", "expanded": true, "quicklink_expanded": false, "search_text": "", "shortcut": null, "saved_root_item_creation_date_time": null, "creation_date_time": 1581595975.6828687, "selected": false, "planned": 0, "planned_order": 0}, {"childItems": [], "text": "Niech zapami\u0119tuje wprowadzony tekst.", "type": "note", "date": "", "color": "NO_COLOR", "estimate": "", "expanded": true, "quicklink_expanded": false, "search_text": "", "shortcut": null, "saved_root_item_creation_date_time": null, "creation_date_time": 1581338488.60448, "selected": false, "planned": 0, "planned_order": 0}, {"childItems": [], "text": "niech zapisuje warto\u015b\u0107 wype\u0142nionych linii", "type": "note", "date": "", "color": "NO_COLOR", "estimate": "", "expanded": true, "quicklink_expanded": false, "search_text": "", "shortcut": null, "saved_root_item_creation_date_time": null, "creation_date_time": 1581338986.9989858, "selected": false, "planned": 0, "planned_order": 0}, {"childItems": [], "text": "pokolorowa\u0107 warto\u015bci przesuwanych element\u00f3w", "type": "note", "date": "", "color": "NO_COLOR", "estimate": "", "expanded": true, "quicklink_expanded": false, "search_text": "", "shortcut": null, "saved_root_item_creation_date_time": null, "creation_date_time": 1581668941.524545, "selected": false, "planned": 0, "planned_order": 0}, {"childItems": [], "text": "powyr\u00f3wnywa\u0107 kreski w aplikacji, zeby by\u0142a lepsza symetria, bo wygl\u0105da semi pro", "type": "note", "date": "", "color": "NO_COLOR", "estimate": "", "expanded": true, "quicklink_expanded": false, "search_text": "", "shortcut": null, "saved_root_item_creation_date_time": null, "creation_date_time": 1581426341.8646152, "selected": false, "planned": 0, "planned_order": 0}, {"childItems": [], "text": "doda\u0107 czarny theme", "type": "note", "date": "", "color": "NO_COLOR", "estimate": "", "expanded": true, "quicklink_expanded": false, "search_text": "", "shortcut": null, "saved_root_item_creation_date_time": null, "creation_date_time": 1581668952.7247138, "selected": false, "planned": 0, "planned_order": 0}, {"childItems": [], "text": "poprawi\u0107 landplace design, np. przez wymuszenie tego kt\u00f3ry jest", "type": "note", "date": "", "color": "NO_COLOR", "estimate": "", "expanded": true, "quicklink_expanded": false, "search_text": "", "shortcut": null, "saved_root_item_creation_date_time": null, "creation_date_time": 1581667439.334428, "selected": false, "planned": 0, "planned_order": 0}, {"childItems": [], "text": "stworzy\u0107 obrazki do aplikacji", "type": "note", "date": "", "color": "NO_COLOR", "estimate": "", "expanded": true, "quicklink_expanded": false, "search_text": "", "shortcut": null, "saved_root_item_creation_date_time": null, "creation_date_time": 1581668994.5962288, "selected": false, "planned": 0, "planned_order": 0}, {"childItems": [], "text": "warto\u015bci negatywne s\u0105 obrucone o 180 stopni", "type": "note", "date": "", "color": "NO_COLOR", "estimate": "", "expanded": true, "quicklink_expanded": false, "search_text": "", "shortcut": null, "saved_root_item_creation_date_time": null, "creation_date_time": 1581681885.8263483, "selected": false, "planned": 0, "planned_order": 0}, {"childItems": [], "text": "usun\u0105\u0107 obw\u00f3dk\u0119 z przesuwanych negative warto\u015bci", "type": "note", "date": "", "color": "NO_COLOR", "estimate": "", "expanded": true, "quicklink_expanded": false, "search_text": "", "shortcut": null, "saved_root_item_creation_date_time": null, "creation_date_time": 1581681872.0023775, "selected": false, "planned": 0, "planned_order": 0}, {"childItems": [], "text": "doda\u0107 apke do AppStore'a", "type": "note", "date": "", "color": "NO_COLOR", "estimate": "", "expanded": true, "quicklink_expanded": false, "search_text": "", "shortcut": null, "saved_root_item_creation_date_time": null, "creation_date_time": 1581668986.436446, "selected": false, "planned": 0, "planned_order": 0}], "text": "Sko\u0144czy\u0107 bucket app", "type": "note", "date": "", "color": "NO_COLOR", "estimate": "", "expanded": true, "quicklink_expanded": false, "search_text": "", "shortcut": null, "saved_root_item_creation_date_time": null, "creation_date_time": 1581338059.9101033, "selected": false, "planned": 0, "planned_order": 0}], "text": "/", "type": "note", "date": "", "color": "NO_COLOR", "estimate": "", "expanded": true, "quicklink_expanded": false, "search_text": "", "shortcut": null, "saved_root_item_creation_date_time": null, "creation_date_time": 1582626927.3264167, "selected": false, "planned": 0, "planned_order": 0, "header_list": ["Text", "Estimate", "Start date"]}, {"childItems": [{"childItems": [], "text": "This is your first entry. Hit 'return' to create another one.", "type": "note", "date": "", "color": "NO_COLOR", "estimate": "", "expanded": false, "quicklink_expanded": false, "search_text": "", "shortcut": null, "saved_root_item_creation_date_time": null, "creation_date_time": 1582626927.3264434, "selected": false, "planned": 0, "planned_order": 0}], "text": "/", "type": "note", "date": "", "color": "NO_COLOR", "estimate": "", "expanded": false, "quicklink_expanded": false, "search_text": "", "shortcut": null, "saved_root_item_creation_date_time": null, "creation_date_time": 1582626927.3264399, "selected": false, "planned": 0, "planned_order": 0, "header_list": ["Bookmarks"]}]